geofred/__init__.py
geofred/geofred.py
geofred/utils.py
geofred/storage/__init__.py
geofred/storage/location_lookup.csv
geofred/storage/location_lookup.py
geofred/storage/state.csv
geofred/storage/state.py
geofred-0.1.2.dist-info/LICENSE
geofred-0.1.2.dist-info/METADATA
geofred-0.1.2.dist-info/WHEEL
geofred-0.1.2.dist-info/top_level.txt
geofred-0.1.2.dist-info/RECORD
