Metadata-Version: 2.1
Name: geofred
Version: 0.1.2
Summary: A wrapper around "zachwill/fred" FRED API that provides easier handling of locations and aggregation types.
Home-page: https://github.com/slee981/geofred
Author: Stephen Lee
Author-email: smlee.981@gmail.com
License: BSD 2-clause
Classifier: License :: OSI Approved :: BSD License
Classifier: Programming Language :: Python :: 3.5
License-File: LICENSE
Requires-Dist: pandas
Requires-Dist: numpy
Requires-Dist: fred
